{
    "blogs" : [
        {
            "title": "This My First Blog",
            "body": "Hello There I learn React js Today",
            "author": "Yasser",
            "id": 1
        },
        {
            "title": "This My Second Blog",
            "body": "React JS not fun",
            "author": "Yasser",
            "id": 2
        },
        {
            "title": "This My Third Blog",
            "body": "React JS, I cant even react",
            "author": "Antonio",
            "id": 3
        }
    ]
}